README.md
setup.py
pymuplot/__init__.py
pymuplot/phasor.py
pymuplot/waveform.py
pymuplot.egg-info/PKG-INFO
pymuplot.egg-info/SOURCES.txt
pymuplot.egg-info/dependency_links.txt
pymuplot.egg-info/requires.txt
pymuplot.egg-info/top_level.txt
test/test_init.py
test/test_multiwaveform.py
test/test_phasor.py
test/test_waveform.py