Metadata-Version: 1.1
Name: pymuplot
Version: 0.2.0
Summary:  Pymuplot provides plotting of PMU data.
Home-page: https://github.com/aleneus/pymuplot
Author: Aleksandr Popov
Author-email: aleneus@gmail.com
License: LGPLv3
Keywords: synchrophasor
Platform: UNKNOWN
Classifier: Development Status :: 3 - Alpha
Classifier: Environment :: X11 Applications :: Qt
Classifier: Intended Audience :: Science/Research
Classifier: Intended Audience :: Developers
Classifier: License :: OSI Approved :: GNU Lesser General Public License v3 (LGPLv3)
Classifier: Operating System :: POSIX :: Linux
Classifier: Operating System :: Microsoft :: Windows
Classifier: Programming Language :: Python :: 3
Classifier: Topic :: Scientific/Engineering
